CHANGELOG.txt
LICENCE.txt
MANIFEST.in
README.txt
setup.py
ptrFinance/__init__.py
ptrFinance/repetitionCSV.csv
ptrFinance/repetitionFunction.py
ptrFinance.egg-info/PKG-INFO
ptrFinance.egg-info/SOURCES.txt
ptrFinance.egg-info/dependency_links.txt
ptrFinance.egg-info/requires.txt
ptrFinance.egg-info/top_level.txt
ptrFinance/__pycache__/repetitionFunction.cpython-310.pyc