Metadata-Version: 2.1
Name: ptrFinance
Version: 0.0.12
Summary: Financial Web Scraping Library
Home-page: 
Author: Rocco Pio Maria Petruccio
Author-email: whatsappbackuprocco@gmail.com
License: MIT
Keywords: Web Scraping,Finance
Classifier: Development Status :: 5 - Production/Stable
Classifier: Intended Audience :: Financial and Insurance Industry
Classifier: Operating System :: Microsoft :: Windows :: Windows 10
Classifier: License :: OSI Approved :: MIT License
Classifier: Programming Language :: Python :: 3
License-File: LICENCE.txt
